pyshoket/__init__.py
pyshoket/utils.py
pyshoket-0.2.3.dist-info/LICENCE
pyshoket-0.2.3.dist-info/METADATA
pyshoket-0.2.3.dist-info/WHEEL
pyshoket-0.2.3.dist-info/top_level.txt
pyshoket-0.2.3.dist-info/RECORD
