Metadata-Version: 2.1
Name: pyshoket
Version: 0.2.3
Summary: A Python wrapper for Shoket API
Home-page: https://github.com/maen08/pyshoket
Author: Stanley Ruheza
Author-email: 2001stany@gmail.com
License: MIT
Download-URL: https://github.com/maen08/pyshoket/archive/refs/tags/v0.2.3.tar.gz
Keywords: shoket,online payment,python
Platform: UNKNOWN
Classifier: Development Status :: 3 - Alpha
Classifier: Environment :: Web Environment
Classifier: Intended Audience :: Developers
Classifier: Topic :: Software Development :: Build Tools
Classifier: License :: OSI Approved :: MIT License
Classifier: Operating System :: OS Independent
Classifier: Programming Language :: Python :: 3.8
Requires-Dist: certifi (==2021.10.8)
Requires-Dist: charset-normalizer (==2.0.12)
Requires-Dist: idna (==3.3)
Requires-Dist: python-decouple (==3.6)
Requires-Dist: requests (==2.27.1)
Requires-Dist: urllib3 (==1.26.8)
